{
    "basic_info": {
      "name": "Harper Foley",
      "titles": [ "Bombs => Banking => Blockchain | If it can be done, I will figure it out" ],
      "social": [
        {
          "name": "github",
          "url": "https://github.com/hfoley2013",
          "class": "fab fa-github"
        },
        {
          "name": "instagram",
          "url": "https://www.instagram.com/rainier_racing_nft/?hl=en",
          "class": "fab fa-instagram"
        },
        {
          "name": "twitter",
          "url": "https://twitter.com/RainierRacingCo",
          "class": "fab fa-twitter"
        }
      ],
      "image": "myProfile.jpg"
    },
    "skills": {
      "icons": [
        {
          "name": "HTML 5",
          "class": "devicon-html5-plain",
          "level": "95"
        },
        {
          "name": "CSS 3",
          "class": "devicon-css3-plain",
          "level": "95"
        },
        {
          "name": "Angular",
          "class": "devicon-angularjs-plain",
          "level": "80"
        },
        {
          "name": "TypeScript",
          "class": "devicon-typescript-plain",
          "level": "90"
        },
        {
          "name": "JavaScript",
          "class": "devicon-javascript-plain",
          "level": "70"
        },
        {
          "name": "Sass",
          "class": "devicon-sass-original",
          "level": "75"
        },
        {
          "name": "Bootstrap",
          "class": "devicon-bootstrap-plain",
          "level": "85"
        },
        {
          "name": "C#",
          "class": "devicon-csharp-plain",
          "level": "65"
        },
        {
          "name": "MySql",
          "class": "devicon-mysql-plain",
          "level": "60"
        }
      ]
    }
  }
